onelake_shortcut_tools/__init__.py
onelake_shortcut_tools/compat_test.py
onelake_shortcut_tools/compatibility_checker.py
onelake_shortcut_tools-0.1.2.dist-info/LICENSE
onelake_shortcut_tools-0.1.2.dist-info/METADATA
onelake_shortcut_tools-0.1.2.dist-info/WHEEL
onelake_shortcut_tools-0.1.2.dist-info/top_level.txt
onelake_shortcut_tools-0.1.2.dist-info/RECORD
