Metadata-Version: 2.1
Name: onelake-shortcut-tools
Version: 0.1.2
Summary: A library of tools for OneLake shortcuts.
Author-email: Miles Cole <m.w.c.360@gmail.com>
License: MIT License
Project-URL: Homepage, https://github.com/mwc360/onelake-shortcut-tools/
Project-URL: Issues, https://github.com/mwc360/onelake-shortcut-tools/issues
Classifier: Programming Language :: Python :: 3
Classifier: License :: OSI Approved :: MIT License
Classifier: Operating System :: OS Independent
Requires-Python: >=3.8
License-File: LICENSE
